mcp_odds_api/__init__.py
mcp_odds_api/main.py
mcp_odds_api/mcp_config.py
mcp_odds_api/server.py
mcp_odds_api/utils.py
mcp_odds_api-0.1.1.dist-info/licenses/LICENSE
mcp_odds_api-0.1.1.dist-info/METADATA
mcp_odds_api-0.1.1.dist-info/WHEEL
mcp_odds_api-0.1.1.dist-info/entry_points.txt
mcp_odds_api-0.1.1.dist-info/top_level.txt
mcp_odds_api-0.1.1.dist-info/RECORD
