Metadata-Version: 2.4
Name: mcp-odds-api
Version: 0.1.1
Summary: An MCP server to interact with a the the odds-api API.
Requires-Python: >=3.9
License-File: LICENSE
Requires-Dist: requests>=2.32
Requires-Dist: mcp>=1.0.0
Requires-Dist: python-dotenv>=1.0.1
Requires-Dist: uvicorn>=0.27.0
Requires-Dist: starlette>=0.36.0
Requires-Dist: typer>=0.15.2
Requires-Dist: fastmcp>=0.4.1
Requires-Dist: httpx
Dynamic: license-file
